argue/__init__.py
argue/argumentative.py
argue-0.3.0.dist-info/METADATA
argue-0.3.0.dist-info/RECORD
argue-0.3.0.dist-info/WHEEL
argue-0.3.0.dist-info/top_level.txt
tests/__init__.py
tests/test_argue.py
